scan_chain/rtl/scan_ff.sv
module scan_ff #(parameter int  width = 1)(
    input logic  clk,
    input logic [width-1:0]  scan_input,
    input logic [width-1:0] d, // data input (regular operation)
    input logic reset, 
    input logic scan_enable, // 1: SHIFT Mode (load from scan chain) 
    // 0: Normal Operation (Capture Mode)
    output logic [width-1:0] Q,
    output  wire [width-1:0] so
);
assign so = Q;
always_ff @(posedge clk) begin
    if (reset) Q <= '0;
    else Q <= scan_enable ? scan_input: d;
end






// SHIFT MODE (scan_en=1):  SI → FF[0].q → FF[1].q → ... → SO
// CAPTURE MODE (scan_en=0): apply 1 functional clock, capture logic values
// Then SHIFT MODE again to read out captured values at SO

endmodule

scan_chain/rtl/scan_chain.sv
module scan_chain #(parameter int width = 1
)(
    input logic clk,
    input logic reset,
    input logic scan_enable,
    input logic [width-1:0] d [0:3],
    input logic [width-1:0] scan_input,
    output reg [width-1:0] Q [0:3],
    output logic [width-1:0] scan_out
);

wire [width-1:0] so [0:3];
scan_ff #(width) ff1(.scan_input(scan_input), .reset(reset), .scan_enable(scan_enable), .clk(clk), .d(d[0]), .Q(Q[0]), .so(so[0]));
scan_ff #(width) ff2(.scan_input(so[0]), .reset(reset), .scan_enable(scan_enable), .clk(clk), .d(d[1]), .Q(Q[1]), .so(so[1]));
scan_ff #(width) ff3(.scan_input(so[1]), .reset(reset), .scan_enable(scan_enable), .clk(clk), .d(d[2]), .Q(Q[2]), .so(so[2]));
scan_ff #(width) ff4(.scan_input(so[2]), .reset(reset), .scan_enable(scan_enable), .clk(clk), .d(d[3]), .Q(Q[3]), .so(so[3]));

assign scan_out = so[3];






endmodule

scan_chain/tb/dump.vcd
$version Generated by VerilatedVcd $end
$timescale 1ps $end
 $scope module $rootio $end
  $var wire 1 " clk $end
  $var wire 1 # reset $end
  $var wire 1 $ scan_enable $end
  $var wire 8 % d[0] [7:0] $end
  $var wire 8 & d[1] [7:0] $end
  $var wire 8 ' d[2] [7:0] $end
  $var wire 8 ( d[3] [7:0] $end
  $var wire 8 ) scan_input [7:0] $end
  $var wire 8 * Q[0] [7:0] $end
  $var wire 8 + Q[1] [7:0] $end
  $var wire 8 , Q[2] [7:0] $end
  $var wire 8 - Q[3] [7:0] $end
  $var wire 8 . scan_out [7:0] $end
 $upscope $end
 $scope module scan_chain $end
  $var wire 32 \ width [31:0] $end
  $var wire 1 / clk $end
  $var wire 1 0 reset $end
  $var wire 1 1 scan_enable $end
  $var wire 8 2 d[0] [7:0] $end
  $var wire 8 3 d[1] [7:0] $end
  $var wire 8 4 d[2] [7:0] $end
  $var wire 8 5 d[3] [7:0] $end
  $var wire 8 6 scan_input [7:0] $end
  $var wire 8 7 Q[0] [7:0] $end
  $var wire 8 8 Q[1] [7:0] $end
  $var wire 8 9 Q[2] [7:0] $end
  $var wire 8 : Q[3] [7:0] $end
  $var wire 8 ; scan_out [7:0] $end
  $var wire 8 < so[0] [7:0] $end
  $var wire 8 = so[1] [7:0] $end
  $var wire 8 > so[2] [7:0] $end
  $var wire 8 ? so[3] [7:0] $end
  $scope module ff1 $end
   $var wire 32 \ width [31:0] $end
   $var wire 1 @ clk $end
   $var wire 8 A scan_input [7:0] $end
   $var wire 8 B d [7:0] $end
   $var wire 1 C reset $end
   $var wire 1 D scan_enable $end
   $var wire 8 E Q [7:0] $end
   $var wire 8 F so [7:0] $end
  $upscope $end
  $scope module ff2 $end
   $var wire 32 \ width [31:0] $end
   $var wire 1 G clk $end
   $var wire 8 H scan_input [7:0] $end
   $var wire 8 I d [7:0] $end
   $var wire 1 J reset $end
   $var wire 1 K scan_enable $end
   $var wire 8 L Q [7:0] $end
   $var wire 8 M so [7:0] $end
  $upscope $end
  $scope module ff3 $end
   $var wire 32 \ width [31:0] $end
   $var wire 1 N clk $end
   $var wire 8 O scan_input [7:0] $end
   $var wire 8 P d [7:0] $end
   $var wire 1 Q reset $end
   $var wire 1 R scan_enable $end
   $var wire 8 S Q [7:0] $end
   $var wire 8 T so [7:0] $end
  $upscope $end
  $scope module ff4 $end
   $var wire 32 \ width [31:0] $end
   $var wire 1 U clk $end
   $var wire 8 V scan_input [7:0] $end
   $var wire 8 W d [7:0] $end
   $var wire 1 X reset $end
   $var wire 1 Y scan_enable $end
   $var wire 8 Z Q [7:0] $end
   $var wire 8 [ so [7:0] $end
  $upscope $end
 $upscope $end
$enddefinitions $end


#0
1"
1#
0$
b00000000 %
b00000000 &
b00000000 '
b00000000 (
b00000000 )
b00000000 *
b00000000 +
b00000000 ,
b00000000 -
b00000000 .
1/
10
01
b00000000 2
b00000000 3
b00000000 4
b00000000 5
b00000000 6
b00000000 7
b00000000 8
b00000000 9
b00000000 :
b00000000 ;
b00000000 <
b00000000 =
b00000000 >
b00000000 ?
1@
b00000000 A
b00000000 B
1C
0D
b00000000 E
b00000000 F
1G
b00000000 H
b00000000 I
1J
0K
b00000000 L
b00000000 M
1N
b00000000 O
b00000000 P
1Q
0R
b00000000 S
b00000000 T
1U
b00000000 V
b00000000 W
1X
0Y
b00000000 Z
b00000000 [
b00000000000000000000000000001000 \
#5000
0"
0#
1$
b10101010 )
0/
00
11
b10101010 6
0@
b10101010 A
0C
1D
0G
0J
1K
0N
0Q
1R
0U
0X
1Y
#10000
1"
b10101010 *
1/
b10101010 7
b10101010 <
1@
b10101010 E
b10101010 F
1G
b10101010 H
1N
1U
#15000
0"
b10111011 )
0/
b10111011 6
0@
b10111011 A
0G
0N
0U
#20000
1"
b10111011 *
b10101010 +
1/
b10111011 7
b10101010 8
b10111011 <
b10101010 =
1@
b10111011 E
b10111011 F
1G
b10111011 H
b10101010 L
b10101010 M
1N
b10101010 O
1U
#25000
0"
b11001100 )
0/
b11001100 6
0@
b11001100 A
0G
0N
0U
#30000
1"
b11001100 *
b10111011 +
b10101010 ,
1/
b11001100 7
b10111011 8
b10101010 9
b11001100 <
b10111011 =
b10101010 >
1@
b11001100 E
b11001100 F
1G
b11001100 H
b10111011 L
b10111011 M
1N
b10111011 O
b10101010 S
b10101010 T
1U
b10101010 V
#35000
0"
b11011101 )
0/
b11011101 6
0@
b11011101 A
0G
0N
0U
#40000
1"
b11011101 *
b11001100 +
b10111011 ,
b10101010 -
b10101010 .
1/
b11011101 7
b11001100 8
b10111011 9
b10101010 :
b10101010 ;
b11011101 <
b11001100 =
b10111011 >
b10101010 ?
1@
b11011101 E
b11011101 F
1G
b11011101 H
b11001100 L
b11001100 M
1N
b11001100 O
b10111011 S
b10111011 T
1U
b10111011 V
b10101010 Z
b10101010 [
#45000
0"
0$
b10001110 %
b10011001 &
b10111101 '
b01010011 (
0/
01
b10001110 2
b10011001 3
b10111101 4
b01010011 5
0@
b10001110 B
0D
0G
b10011001 I
0K
0N
b10111101 P
0R
0U
b01010011 W
0Y
#50000
1"
b10001110 *
b10011001 +
b10111101 ,
b01010011 -
b01010011 .
1/
b10001110 7
b10011001 8
b10111101 9
b01010011 :
b01010011 ;
b10001110 <
b10011001 =
b10111101 >
b01010011 ?
1@
b10001110 E
b10001110 F
1G
b10001110 H
b10011001 L
b10011001 M
1N
b10011001 O
b10111101 S
b10111101 T
1U
b10111101 V
b01010011 Z
b01010011 [
#55000
0"
1$
b10101010 )
0/
11
b10101010 6
0@
b10101010 A
1D
0G
1K
0N
1R
0U
1Y
#60000
1"
b10101010 *
b10001110 +
b10011001 ,
b10111101 -
b10111101 .
1/
b10101010 7
b10001110 8
b10011001 9
b10111101 :
b10111101 ;
b10101010 <
b10001110 =
b10011001 >
b10111101 ?
1@
b10101010 E
b10101010 F
1G
b10101010 H
b10001110 L
b10001110 M
1N
b10001110 O
b10011001 S
b10011001 T
1U
b10011001 V
b10111101 Z
b10111101 [
