scan_chain/rtl/scan_ff.sv
module scan_ff #(parameter int  width = 1)(
    input logic  clk,
    input logic [width-1:0]  scan_input,
    input logic [width-1:0] d, // data input (regular operation)
    input logic reset, 
    input logic scan_enable, // 1: SHIFT Mode (load from scan chain) 
    // 0: Normal Operation (Capture Mode)
    output logic [width-1:0] Q,
    output  wire [width-1:0] so
);
assign so = Q;
always_ff @(posedge clk) begin
    if (reset) Q <= '0;
    else Q <= scan_enable ? scan_input: d;
end






// SHIFT MODE (scan_en=1):  SI → FF[0].q → FF[1].q → ... → SO
// CAPTURE MODE (scan_en=0): apply 1 functional clock, capture logic values
// Then SHIFT MODE again to read out captured values at SO

endmodule

scan_chain/rtl/scan_chain.sv
module scan_chain #(parameter int width = 1
)(
    input logic clk,
    input logic reset,
    input logic scan_enable,
    input logic [width-1:0] d [0:3],
    input logic [width-1:0] scan_input,
    output reg [width-1:0] Q [0:3],
    output logic [width-1:0] scan_out
);

wire [width-1:0] so [0:3];
scan_ff #(width) ff1(.scan_input(scan_input), .reset(reset), .scan_enable(scan_enable), .clk(clk), .d(d[0]), .Q(Q[0]), .so(so[0]));
scan_ff #(width) ff2(.scan_input(so[0]), .reset(reset), .scan_enable(scan_enable), .clk(clk), .d(d[1]), .Q(Q[1]), .so(so[1]));
scan_ff #(width) ff3(.scan_input(so[1]), .reset(reset), .scan_enable(scan_enable), .clk(clk), .d(d[2]), .Q(Q[2]), .so(so[2]));
scan_ff #(width) ff4(.scan_input(so[2]), .reset(reset), .scan_enable(scan_enable), .clk(clk), .d(d[3]), .Q(Q[3]), .so(so[3]));

assign scan_out = so[3];






endmodule

scan_chain/scan_chain.vcd
$version Generated by VerilatedVcd $end
$timescale 1ps $end
 $scope module TOP $end
  $var wire 1 * clk $end
  $var wire 1 + reset $end
  $var wire 1 , scan_enable $end
  $var wire 8 - d[0] [7:0] $end
  $var wire 8 . d[1] [7:0] $end
  $var wire 8 / d[2] [7:0] $end
  $var wire 8 0 d[3] [7:0] $end
  $var wire 8 1 scan_input [7:0] $end
  $var wire 8 2 Q[0] [7:0] $end
  $var wire 8 3 Q[1] [7:0] $end
  $var wire 8 4 Q[2] [7:0] $end
  $var wire 8 5 Q[3] [7:0] $end
  $var wire 8 " scan_out [7:0] $end
  $scope module scan_chain $end
   $var wire 32 : width [31:0] $end
   $var wire 1 * clk $end
   $var wire 1 + reset $end
   $var wire 1 , scan_enable $end
   $var wire 8 - d[0] [7:0] $end
   $var wire 8 . d[1] [7:0] $end
   $var wire 8 / d[2] [7:0] $end
   $var wire 8 0 d[3] [7:0] $end
   $var wire 8 1 scan_input [7:0] $end
   $var wire 8 2 Q[0] [7:0] $end
   $var wire 8 3 Q[1] [7:0] $end
   $var wire 8 4 Q[2] [7:0] $end
   $var wire 8 5 Q[3] [7:0] $end
   $var wire 8 " scan_out [7:0] $end
   $var wire 8 # so[0] [7:0] $end
   $var wire 8 $ so[1] [7:0] $end
   $var wire 8 % so[2] [7:0] $end
   $var wire 8 & so[3] [7:0] $end
   $scope module ff1 $end
    $var wire 32 : width [31:0] $end
    $var wire 1 * clk $end
    $var wire 8 1 scan_input [7:0] $end
    $var wire 8 6 d [7:0] $end
    $var wire 1 + reset $end
    $var wire 1 , scan_enable $end
    $var wire 8 ' Q [7:0] $end
    $var wire 8 ' so [7:0] $end
   $upscope $end
   $scope module ff2 $end
    $var wire 32 : width [31:0] $end
    $var wire 1 * clk $end
    $var wire 8 ' scan_input [7:0] $end
    $var wire 8 7 d [7:0] $end
    $var wire 1 + reset $end
    $var wire 1 , scan_enable $end
    $var wire 8 ( Q [7:0] $end
    $var wire 8 ( so [7:0] $end
   $upscope $end
   $scope module ff3 $end
    $var wire 32 : width [31:0] $end
    $var wire 1 * clk $end
    $var wire 8 ( scan_input [7:0] $end
    $var wire 8 8 d [7:0] $end
    $var wire 1 + reset $end
    $var wire 1 , scan_enable $end
    $var wire 8 ) Q [7:0] $end
    $var wire 8 ) so [7:0] $end
   $upscope $end
   $scope module ff4 $end
    $var wire 32 : width [31:0] $end
    $var wire 1 * clk $end
    $var wire 8 ) scan_input [7:0] $end
    $var wire 8 9 d [7:0] $end
    $var wire 1 + reset $end
    $var wire 1 , scan_enable $end
    $var wire 8 " Q [7:0] $end
    $var wire 8 " so [7:0] $end
   $upscope $end
  $upscope $end
 $upscope $end
$enddefinitions $end


#0
b00000000 "
b00000000 #
b00000000 $
b00000000 %
b00000000 &
b00000000 '
b00000000 (
b00000000 )
0*
0+
0,
b00001000 -
b00110010 .
b01001010 /
b00111011 0
b00000100 1
b00000000 2
b00000000 3
b00000000 4
b00000000 5
b00001000 6
b00110010 7
b01001010 8
b00111011 9
b00000000000000000000000000001000 :
#1
1+
#2
1*
#3
0*
0+
1,
#4
b00000100 #
b00000100 '
1*
b00000100 2
#5
0*
b00000101 1
#6
b00000101 #
b00000100 $
b00000101 '
b00000100 (
1*
b00000101 2
b00000100 3
#7
0*
b00000110 1
#8
b00000110 #
b00000101 $
b00000100 %
b00000110 '
b00000101 (
b00000100 )
1*
b00000110 2
b00000101 3
b00000100 4
#9
0*
b00000111 1
#10
b00000100 "
b00000111 #
b00000110 $
b00000101 %
b00000100 &
b00000111 '
b00000110 (
b00000101 )
1*
b00000111 2
b00000110 3
b00000101 4
b00000100 5
