scan_chain/rtl/scan_ff.sv
module scan_ff #(parameter int  width = 1)(
    input logic  clk,
    input logic [width-1:0]  scan_input,
    input logic [width-1:0] d, // data input (regular operation)
    input logic reset, 
    input logic scan_enable, // 1: SHIFT Mode (load from scan chain) 
    // 0: Normal Operation (Capture Mode)
    output logic [width-1:0] Q,
    output  wire [width-1:0] so
);
assign so = Q;
always_ff @(posedge clk) begin
    if (reset) Q <= '0;
    else Q <= scan_enable ? scan_input: d;
end






// SHIFT MODE (scan_en=1):  SI → FF[0].q → FF[1].q → ... → SO
// CAPTURE MODE (scan_en=0): apply 1 functional clock, capture logic values
// Then SHIFT MODE again to read out captured values at SO

endmodule

scan_chain/scan_ff.vcd
$version Generated by VerilatedVcd $end
$timescale 1ps $end
 $scope module TOP $end
  $var wire 1 " clk $end
  $var wire 1 # scan_input [0:0] $end
  $var wire 1 $ d [0:0] $end
  $var wire 1 % reset $end
  $var wire 1 & scan_enable $end
  $var wire 1 ' Q [0:0] $end
  $var wire 1 ' so [0:0] $end
  $scope module scan_ff $end
   $var wire 32 ( width [31:0] $end
   $var wire 1 " clk $end
   $var wire 1 # scan_input [0:0] $end
   $var wire 1 $ d [0:0] $end
   $var wire 1 % reset $end
   $var wire 1 & scan_enable $end
   $var wire 1 ' Q [0:0] $end
   $var wire 1 ' so [0:0] $end
  $upscope $end
 $upscope $end
$enddefinitions $end


#0
0"
0#
0$
0%
0&
0'
b00000000000000000000000000000001 (
#1
1$
#2
1"
1'
#3
0"
1&
#4
1"
0'
#5
0"
1#
#6
1"
1'
#7
1%
#8
0"
#9
1"
0'
